LICENSE
MANIFEST.in
README.rst
setup.py
docs/Makefile
docs/build/doctrees/changing html.doctree
docs/build/doctrees/environment.pickle
docs/build/doctrees/index.doctree
docs/build/doctrees/installation.doctree
docs/build/doctrees/intro.doctree
docs/build/doctrees/tutorial.doctree
docs/build/doctrees/using in browser.doctree
docs/build/doctrees/using in code.doctree
docs/build/html/.buildinfo
docs/build/html/changing html.html
docs/build/html/genindex.html
docs/build/html/index.html
docs/build/html/installation.html
docs/build/html/objects.inv
docs/build/html/search.html
docs/build/html/searchindex.js
docs/build/html/tutorial.html
docs/build/html/using in browser.html
docs/build/html/using in code.html
docs/build/html/_sources/changing html.txt
docs/build/html/_sources/index.txt
docs/build/html/_sources/installation.txt
docs/build/html/_sources/tutorial.txt
docs/build/html/_sources/using in browser.txt
docs/build/html/_sources/using in code.txt
docs/build/html/_static/ajax-loader.gif
docs/build/html/_static/alabaster.css
docs/build/html/_static/basic.css
docs/build/html/_static/comment-bright.png
docs/build/html/_static/comment-close.png
docs/build/html/_static/comment.png
docs/build/html/_static/doctools.js
docs/build/html/_static/down-pressed.png
docs/build/html/_static/down.png
docs/build/html/_static/file.png
docs/build/html/_static/jquery-1.11.1.js
docs/build/html/_static/jquery.js
docs/build/html/_static/minus.png
docs/build/html/_static/plus.png
docs/build/html/_static/pygments.css
docs/build/html/_static/searchtools.js
docs/build/html/_static/underscore-1.3.1.js
docs/build/html/_static/underscore.js
docs/build/html/_static/up-pressed.png
docs/build/html/_static/up.png
docs/build/html/_static/websupport.js
docs/source/changing html.rst
docs/source/conf.py
docs/source/index.rst
docs/source/installation.rst
docs/source/sample.html
docs/source/tutorial.rst
docs/source/using in browser.rst
docs/source/using in code.rst
templado/__init__.py
templado/admin.py
templado.egg-info/PKG-INFO
templado.egg-info/SOURCES.txt
templado.egg-info/dependency_links.txt
templado.egg-info/requires.txt
templado.egg-info/top_level.txt
