Metadata-Version: 1.1
Name: templado
Version: 0.5.9
Summary: Templado is a simple Django app to upload your HTML report templates and generate PDF reports by filling the fields of form based on JSON template.
Home-page: https://github.com/nnkps/templado
Author: Anna Kups
Author-email: aniakups@gmail.com
License: BSD License
Keywords: template json html pdf report invoice
Platform: UNKNOWN
Classifier: Environment :: Web Environment
Classifier: Framework :: Django
Classifier: Intended Audience :: Developers
Classifier: License :: OSI Approved :: BSD License
Classifier: Operating System :: OS Independent
Classifier: Programming Language :: Python
Classifier: Programming Language :: Python :: 2
Classifier: Programming Language :: Python :: 2.6
Classifier: Programming Language :: Python :: 2.7
Classifier: Topic :: Internet :: WWW/HTTP
Classifier: Topic :: Internet :: WWW/HTTP :: Dynamic Content
